ISOSIMpy/__init__.py
ISOSIMpy/__main__.py
ISOSIMpy/gui/__init__.py
ISOSIMpy/gui/app.py
ISOSIMpy/gui/controller.py
ISOSIMpy/gui/main_window.py
ISOSIMpy/gui/state.py
ISOSIMpy/gui/tabs/file_input.py
ISOSIMpy/gui/tabs/model_design.py
ISOSIMpy/gui/tabs/parameters.py
ISOSIMpy/gui/tabs/simulation.py
ISOSIMpy/gui/tabs/widgets.py
ISOSIMpy/model/__init__.py
ISOSIMpy/model/model.py
ISOSIMpy/model/registry.py
ISOSIMpy/model/solver.py
ISOSIMpy/model/units.py
isosimpy-0.1.11.dist-info/licenses/LICENSE
isosimpy-0.1.11.dist-info/METADATA
isosimpy-0.1.11.dist-info/WHEEL
isosimpy-0.1.11.dist-info/entry_points.txt
isosimpy-0.1.11.dist-info/top_level.txt
isosimpy-0.1.11.dist-info/RECORD
